popcorn_api/__init__.py
popcorn_api/config.json
popcorn_api/popcorn_api.py
popcorn_api-0.0.1a6.dist-info/METADATA
popcorn_api-0.0.1a6.dist-info/WHEEL
popcorn_api-0.0.1a6.dist-info/licenses/LICENSE
popcorn_api-0.0.1a6.dist-info/RECORD
